{
  "IsEncrypted": false,
  "Values": {
    "AzureWebJobsStorage": "UseDevelopmentStorage=true",
    "AzureWebJobsDashboard": "UseDevelopmentStorage=true",
    "FUNCTIONS_WORKER_RUNTIME": "dotnet",
    "UpdatesScrapingCronExpression": "0 0 12 * * MON", // Every Monday at noon
    "WaitAfterServerLimitTimeSpan": "00:00:04",
    "BaseTvMazeApiUri": "http://api.tvmaze.com",
    "DefaultConnection": "Server=(localdb)\\mssqllocaldb;Database=ScraperDatabase;Trusted_Connection=True;MultipleActiveResultSets=true"
  }
}